{
  "id": "c1a0b2d3-0000-4000-8000-chaco0000env",
  "name": "Chaco (local)",
  "values": [
    {
      "key": "base_url",
      "value": "http://localhost:8000",
      "type": "default",
      "enabled": true
    },
    {
      "key": "username",
      "value": "territorial_becas",
      "type": "default",
      "enabled": true
    },
    {
      "key": "password",
      "value": "mkdir123",
      "type": "secret",
      "enabled": true
    },
    {
      "key": "token",
      "value": "",
      "type": "secret",
      "enabled": true
    },
    {
      "key": "relevamiento_id",
      "value": "1",
      "type": "default",
      "enabled": true
    },
    {
      "key": "formulario_id",
      "value": "1",
      "type": "default",
      "enabled": true
    }
  ],
  "_postman_variable_scope": "environment"
}
